Workbook

Sheet Readme
A1: Business Case SEPM – Datenerhebung
A3: Diese Arbeitsmappe dient der Erfassung der Zahlen für den Business Case. Alle mit oranger Hintergrundfarbe markierten Zellen sind Eingabefelder. Blaue/graue Zellen sind berechnet.
A5: Reiter der Arbeitsmappe:
A6: Assumptions | B6: Basis-Annahmen (FTE-Satz, WACC, Jahre)
A7: TCO_Detail | B7: Einmalige + laufende Kosten SEPM, aufgeschlüsselt
A8: Konsolidierung_Tools | B8: Ablöse-Ersparnis pro heutigem Tool (PIT, MSPO, …)
A9: Konsolidierung_Schnittstellen | B9: Ersparnis durch Wegfall von APIs/Integrationen
A10: Support_Kosten | B10: Interner + externer Support/Wartung, Weiterentwicklung
A11: Business_Value | B11: Nutzen-Kategorien mit quantifiziertem Steady State
A12: Prozess_Potentiale | B12: Flankierende Prozesse (Maßnahmen-Mgmt, APM, …)
A13: Szenarien | B13: Szenario A / B / C – Vergleich
A14: SNOW_Vertragshistorie | B14: Vertragshistorie 2014–heute, Preisentwicklung
A15: Risiken | B15: Risiko-Register + Mitigationen
A16: Sensitivity | B16: Best / Base / Worst Case
A17: Auswertung | B17: Executive Summary (automatisch aus obigen Tabs)

Sheet Assumptions
A1: Basis-Annahmen
A3: Parameter | B3: Wert | C3: Einheit
A4: Betrachtungshorizont (Jahre) | B4: 5 | C4: Jahre
A5: FTE-Satz (fully loaded) | B5: 130 | C5: k€ p.a.
A6: WACC (Diskontrate) | B6: 0.06 | C6: %
A7: Startjahr | B7: 2027 | C7: Jahr
A8: Inflations-Annahme | B8: 0.02 | C8: %
A9: Mengengerüst Named User (Start) | B9: 200 | C9: Anzahl
A10: Mengengerüst Named User (Steady) | B10: 400 | C10: Anzahl
A11: Preis pro Named User p.a. | B11: 2000 | C11: €
A12: Externer Support Retainer p.a. | B12: 180 | C12: k€
A13: Contingency (Puffer) | B13: 0.1 | C13: %

Sheet TCO_Detail
A1: TCO-Detail 5 Jahre
A3: Kostenposition | B3: Jahr 1 | C3: Jahr 2 | D3: Jahr 3 | E3: Jahr 4 | F3: Jahr 5 | G3: Summe | H3: Kommentar
A4: Einmalige Kosten
A5: Implementierungs-Partner (SI) | B5: 1300 | C5: 0 | D5: 0 | E5: 0 | F5: 0 | G5: =SUM(B5:F5)
A6: Interne FTE Impl. (in k€) | B6: 520 | C6: 520 | D6: 0 | E6: 0 | F6: 0 | G6: =SUM(B6:F6)
A7: Change / Schulung | B7: 250 | C7: 100 | D7: 0 | E7: 0 | F7: 0 | G7: =SUM(B7:F7)
A8: Contingency (Puffer) | B8: 150 | C8: 100 | D8: 0 | E8: 0 | F8: 0 | G8: =SUM(B8:F8)
A9: Laufende Kosten p.a.
A10: Lizenzen SNOW SPM Pro | B10: 720 | C10: 780 | D10: 850 | E10: 850 | F10: 850 | G10: =SUM(B10:F10)
A11: Interner Betrieb (FTE × Satz) | B11: 260 | C11: 300 | D11: 390 | E11: 390 | F11: 390 | G11: =SUM(B11:F11)
A12: Externer Support / Wartung | B12: 120 | C12: 150 | D12: 180 | E12: 180 | F12: 180 | G12: =SUM(B12:F12)
A13: Weiterentwicklung | B13: 50 | C13: 150 | D13: 220 | E13: 220 | F13: 220 | G13: =SUM(B13:F13)
A14: Summe pro Jahr | B14: =B5+B6+B7+B8+B10+B11+B12+B13 | C14: =C5+C6+C7+C8+C10+C11+C12+C13 | D14: =D5+D6+D7+D8+D10+D11+D12+D13 | E14: =E5+E6+E7+E8+E10+E11+E12+E13 | F14: =F5+F6+F7+F8+F10+F11+F12+F13 | G14: =G5+G6+G7+G8+G10+G11+G12+G13

Sheet Konsolidierung_Tools
A1: Konsolidierungs-Ersparnis: Tool-Ablöse
A3: Tool | B3: Kategorie | C3: Lizenz p.a. (k€) | D3: Wartung p.a. (k€) | E3: FTE-Aufwand (FTE) | F3: FTE-Kosten (k€) | G3: Sonst. (k€) | H3: Ersparnis p.a. (k€)
A4: PIT / PLANTA | B4: Projekt-/Ressourcen-Mgmt | C4: 0 | D4: 0 | E4: 0 | F4: =E4*Assumptions!B5 | G4: 0 | H4: =C4+D4+F4+G4
A5: MS Project Online | B5: Klass. Projekt-Mgmt | C5: 0 | D5: 0 | E5: 0 | F5: =E5*Assumptions!B5 | G5: 0 | H5: =C5+D5+F5+G5
A6: Workpath | B6: Strategie / OKR | C6: 0 | D6: 0 | E6: 0 | F6: =E6*Assumptions!B5 | G6: 0 | H6: =C6+D6+F6+G6
A7: Power Apps | B7: Custom-Formulare | C7: 0 | D7: 0 | E7: 0 | F7: =E7*Assumptions!B5 | G7: 0 | H7: =C7+D7+F7+G7
A8: SharePoint-Listen | B8: Demand-Listen | C8: 0 | D8: 0 | E8: 0 | F8: =E8*Assumptions!B5 | G8: 0 | H8: =C8+D8+F8+G8
A9: Lucom (EV, teilweise) | B9: EV-Prozess | C9: 0 | D9: 0 | E9: 0 | F9: =E9*Assumptions!B5 | G9: 0 | H9: =C9+D9+F9+G9
A10: Summe | C10: =SUM(C4:C9) | D10: =SUM(D4:D9) | E10: =SUM(E4:E9) | F10: =SUM(F4:F9) | G10: =SUM(G4:G9) | H10: =SUM(H4:H9)

Sheet Konsolidierung_Schnittstellen
A1: Konsolidierungs-Ersparnis: Schnittstellen / Integrationen
A3: Schnittstelle heute | B3: Wartungs-PT/Jahr | C3: PT-Satz (€/PT) | D3: Ersparnis Wartung (k€) | E3: Sonst. Betriebskosten (k€) | F3: Ersparnis gesamt (k€)
A4: PIT ↔ SAP FI | B4: 0 | C4: 1200 | D4: =B4*C4/1000 | E4: 0 | F4: =D4+E4
A5: MSPO ↔ SAP HCM | B5: 0 | C5: 1200 | D5: =B5*C5/1000 | E5: 0 | F5: =D5+E5
A6: SharePoint ↔ Excel-Exports | B6: 0 | C6: 1200 | D6: =B6*C6/1000 | E6: 0 | F6: =D6+E6
A7: Workpath ↔ Excel-Reporting | B7: 0 | C7: 1200 | D7: =B7*C7/1000 | E7: 0 | F7: =D7+E7
A8: PowerApps ↔ Dataverse | B8: 0 | C8: 1200 | D8: =B8*C8/1000 | E8: 0 | F8: =D8+E8
A9: Lucom EV ↔ SAP | B9: 0 | C9: 1200 | D9: =B9*C9/1000 | E9: 0 | F9: =D9+E9
A10: Excel-Konsolidierungen (diverse) | B10: 0 | C10: 1200 | D10: =B10*C10/1000 | E10: 0 | F10: =D10+E10
A11: Summe | D11: =SUM(D4:D10) | E11: =SUM(E4:E10) | F11: =SUM(F4:F10)

Sheet Support_Kosten
A1: Support-Kosten: Intern + Extern + Weiterentwicklung
A3: Position | B3: Typ | C3: FTE | D3: Preis (k€) | E3: Kosten p.a. (k€)
A4: SNOW-Plattform-Admin | B4: Intern FTE | C4: 1 | E4: =C4*Assumptions!B5
A5: SPM Business Analyst | B5: Intern FTE | C5: 1 | E5: =C5*Assumptions!B5
A6: Integration/Schnittstellen | B6: Intern FTE | C6: 0.5 | E6: =C6*Assumptions!B5
A7: Data Governance | B7: Intern FTE | C7: 0.3 | E7: =C7*Assumptions!B5
A8: User Support 2nd Level | B8: Intern FTE | C8: 0.2 | E8: =C8*Assumptions!B5
A9: Wartungsvertrag SNOW | B9: Extern | D9: 70 | E9: =D9
A10: Managed Service Partner | B10: Extern | D10: 90 | E10: =D10
A11: Externes Consulting | B11: Extern | D11: 60 | E11: =D11
A12: Zertifizierungen / Training | B12: Extern | D12: 30 | E12: =D12
A13: Feature-Backlog Business | B13: Weiterentw. | D13: 100 | E13: =D13
A14: Release-Upgrade-Anpassungen | B14: Weiterentw. | D14: 50 | E14: =D14
A15: Custom-Reports/Dashboards | B15: Weiterentw. | D15: 40 | E15: =D15
A16: Innovation Sprints | B16: Weiterentw. | D16: 30 | E16: =D16
A17: Summe p.a. | E17: =SUM(E4:E16)

Sheet Business_Value
A1: Business Value: Nutzen-Kategorien
A3: Nutzen-Kategorie | B3: Beschreibung | C3: Berechnungslogik | D3: Menge (Basis) | E3: Wert je Einheit (€) | F3: Nutzen p.a. (k€)
A4: Effizienz PM/PPM | B4: Weniger manuelle Excels/Berichte, Ressourcen-Steuerung | C4: Reporting-PT × PT-Satz | D4: 400 | E4: 1200 | F4: =IFERROR(D4*E4/1000,0)
A5: Time-to-Market | B5: Schnellere Idee→Projekt-Start (Gates in System) | C5: Ø Zeitgewinn × Umsatz p.d. | F5: =IFERROR(D5*E5/1000,0)
A6: Governance / Rework | B6: Weniger Doppelarbeit, klare Priorisierung | C6: Rework-Fälle × Kosten je Fall | F6: =IFERROR(D6*E6/1000,0)
A7: Ressourcen-Optimierung | B7: Skill-Match, Auslastungs-Steuerung | C7: Ausgelastete FTE × Satz × Gewinn % | F7: =IFERROR(D7*E7/1000,0)
A8: Compliance / Audit | B8: Nachvollziehbarkeit, Business Cases im System | C8: Audit-Aufwand-Reduktion | F8: =IFERROR(D8*E8/1000,0)
A9: Summe Nutzen p.a. | F9: =SUM(F4:F8)

Sheet Prozess_Potentiale
A1: Flankierende Prozesse: Zusätzliche Potentiale
A3: Prozess | B3: Beschreibung | C3: Berechnungslogik | D3: Menge | E3: Wert (€) | F3: Ersparnis p.a. (k€)
A4: Maßnahmen-Management im Zielkostenmanagement der Produktentwicklung | B4: Zentraler Maßnahmen-Backlog, Verknüpfung mit Portfolios/Cost-Targets | F4: 380
A5: Innovations- / Vorhaben-Trichter (LH/CRD → Steckbrief → Projekt) | B5: Durchgängige Pipeline; weniger Reibungsverluste | F5: 220
A6: Application Portfolio Mgmt (APM) | B6: Lifecycle-Management der Anwendungslandschaft | F6: 160
A7: Benefits Realization Tracking | B7: Ist-/Soll-Nutzenabgleich nach Projektabschluss | F7: 120
A8: Compliance / EV-Prozess-Digitalisierung | B8: EV-Workflow in SNOW; weniger manuelle Freigabeschleifen | F8: 180
A9: Summe | F9: =SUM(F4:F8)

Sheet Szenarien
A1: Szenarien-Vergleich
A3: Kennzahl | B3: Szenario A (24 Mo, Full) | C3: Szenario B (36 Mo, Extended) | D3: Szenario C (12+18 Mo, MVP)
A4: Dauer (Monate) | B4: 24 | C4: 36 | D4: 30
A5: Einmalige Kosten (k€) | B5: 3000 | C5: 2700 | D5: 2200
A6: Laufend p.a. steady (k€) | B6: 850 | C6: 800 | D6: 700
A7: 5-Jahres-TCO (k€) | B7: =B5+5*B6 | C7: =C5+5*C6 | D7: =D5+5*D6
A8: Nutzen Y3 kumul. (k€) | B8: 3500 | C8: 1800 | D8: 2500
A9: Nutzen Y5 kumul. (k€) | B9: 16000 | C9: 12000 | D9: 13500
A10: Payback (Jahre) | B10: 3.5 | C10: 4.5 | D10: 3
A11: Empfohlen? | B11: ★ Ja | C11: Nein | D11: Nein

Sheet SNOW_Vertragshistorie
A1: ServiceNow: Vertragshistorie 2014 – heute
A3: Jahr | B3: Vertragsstufe | C3: Beschreibung | D3: Named User | E3: Lizenz p.a. (k€) | F3: Δ vs Vorjahr (%) | G3: Sonstige Notizen
A4: 2014 | B4: Erstvertrag ITSM | C4: Standard Package, 500 Fulfiller | E4: 180
A5: 2016 | B5: Erweiterung Global | C5: Ausrollung inkl. China | E5: 260 | F5: =(E5-E4)/E4
A6: 2018 | B6: Enterprise-Vertrag | C6: Volumen-Diskont, HR-SD add-on | E6: 340 | F6: =(E6-E5)/E5
A7: 2020 | B7: ITOM + CMDB | C7: Discovery, Event Mgmt | E7: 410 | F7: =(E7-E6)/E6
A8: 2022 | B8: Contract Renewal 3J | C8: Preisanpassung +5% p.a. | E8: 490 | F8: =(E8-E7)/E7
A9: 2024 | B9: Now Assist Preview | C9: GenAI eingeführt | E9: 560 | F9: =(E9-E8)/E8
A10: 2026 | B10: SPM Pro (geplant) | C10: Neuer Modul-Baustein | E10: 820 | F10: =(E10-E9)/E9

Sheet Risiken
A1: Risiko-Register
A3: # | B3: Risiko | C3: Beschreibung | D3: Wahrsch. (1-5) | E3: Auswirkung (1-5) | F3: Score | G3: Mitigation | H3: Owner | I3: Review Datum
A4: 1 | B4: Vendor Lock-in | D4: 4 | E4: 4 | F4: =D4*E4 | G4: Standard-Konfiguration, Migrations-Klauseln, jährl. Marktscreening
A5: 2 | B5: Preis-Eskalation | D5: 3 | E5: 3 | F5: =D5*E5 | G5: Mehrjahresvertrag mit Preisgarantie, Volumen-Rabatte
A6: 3 | B6: Ausfall/Betrieb | D6: 2 | E6: 2 | F6: =D6*E6 | G6: SLA 99,9% + regionaler DC (Frankfurt/Düsseldorf), DSGVO
A7: 4 | B7: Roadmap-Divergenz | D7: 3 | E7: 3 | F7: =D7*E7 | G7: Standard first, keine tiefen Anpassungen; halbjährl. Review
A8: 5 | B8: Datenhoheit / DSGVO | D8: 2 | E8: 2 | F8: =D8*E8 | G8: DE-Hosting, ADV-Vertrag, verschlüsselte Datenhaltung
A9: 6 | B9: Team-Kompetenzaufbau | D9: 3 | E9: 3 | F9: =D9*E9 | G9: Ausbau ITSM-Team +1,5-2 FTE, Ausbildungsplan, Partner-Support

Sheet Sensitivity
A1: Sensitivitäts-Analyse: Best / Base / Worst Case
A3: Kennzahl | B3: Best Case | C3: Base Case | D3: Worst Case
A4: 5-Jahres-TCO (k€) | B4: 6000 | C4: 7000 | D4: 8500
A5: Konsolidierung Tools 5J (k€) | B5: 5500 | C5: 4700 | D5: 3500
A6: Business Value 5J (k€) | B6: 14000 | C6: 11600 | D6: 8500
A7: Flankierende Prozesse 5J | B7: 6500 | C7: 5300 | D7: 3800
A8: Netto-Effekt 5 Jahre (k€) | B8: =B5+B6+B7-B4 | C8: =C5+C6+C7-C4 | D8: =D5+D6+D7-D4
A9: NPV (WACC 6 %) (k€) | B9: 10500 | C9: 8500 | D9: 6000
A10: IRR (%) | B10: 42 | C10: 32 | D10: 22
A11: Payback (Jahre) | B11: 2.8 | C11: 3.5 | D11: 4.5

Sheet Auswertung
A1: Executive Summary Business Case SEPM
A3: Kennzahl | B3: Wert | C3: Kommentar
A4: 5-Jahres-TCO SEPM | B4: ='TCO_Detail'!G14 | C4: einmalig + laufend
A5: Konsolidierung Tools p.a. | B5: ='Konsolidierung_Tools'!H10 | C5: Steady State
A6: Business Value p.a. | B6: ='Business_Value'!F9 | C6: Steady State
A7: Flankierende Prozesse p.a. | B7: ='Prozess_Potentiale'!F9 | C7: SPM-nah, quantifiziert
A8: Support-Kosten p.a. | B8: ='Support_Kosten'!E17 | C8: intern + extern + Weiterentw.
A9: Payback (Jahre) | B9: ='Sensitivity'!C10 | C9: Base Case
A10: NPV (WACC 6 %) | B10: ='Sensitivity'!C8 | C10: Base Case
A11: IRR | B11: ='Sensitivity'!C9 | C11: Base Case
